pyenv_mirror
tests
