Metadata-Version: 1.1
Name: pyenv-mirror
Version: 0.2.3
Summary: UNKNOWN
Home-page: UNKNOWN
Author: huntzhan
Author-email: programmer.zhx@gmail.com
License: UNKNOWN
Platform: UNKNOWN
Classifier: Development Status :: 4 - Beta
Classifier: Intended Audience :: Developers
Classifier: Topic :: Software Development :: Testing
Classifier: Programming Language :: Python
Classifier: Operating System :: OS Independent
